akwesipackage/__init__.py
akwesipackage-0.1.dist-info/DESCRIPTION.rst
akwesipackage-0.1.dist-info/METADATA
akwesipackage-0.1.dist-info/RECORD
akwesipackage-0.1.dist-info/WHEEL
akwesipackage-0.1.dist-info/metadata.json
akwesipackage-0.1.dist-info/top_level.txt
